robolytix/__init__.py
robolytix/api_client.py
robolytix/configuration.py
robolytix/rest.py
robolytix/api/__init__.py
robolytix/api/common_api.py
robolytix/api/default_api.py
robolytix/models/__init__.py
robolytix/models/inline_response_default.py
robolytix/models/inline_response_default1.py
robolytix/models/inline_response_default2.py
robolytix/models/inline_response_default2_data.py
robolytix/models/message.py
robolytix/models/process.py
robolytix/models/type.py
test/__init__.py
test/test_common_api.py
test/test_default_api.py
test/test_inline_response_default.py
test/test_inline_response_default1.py
test/test_inline_response_default2.py
test/test_inline_response_default2_data.py
test/test_message.py
test/test_process.py
test/test_type.py
robolytix-0.2.1.dist-info/LICENSE
robolytix-0.2.1.dist-info/METADATA
robolytix-0.2.1.dist-info/WHEEL
robolytix-0.2.1.dist-info/top_level.txt
robolytix-0.2.1.dist-info/RECORD
