Metadata-Version: 2.1
Name: robolytix
Version: 0.2.1
Summary: Robolytix is the key online analytic and monitoring tool for Business / Robotic Process Automation.
Home-page: https://github.com/robolytix/robolytix-sdk/
Author: Robolytix.com
Author-email: info@robolytix.com
License: UNKNOWN
Keywords: Client,Robolytix
Platform: UNKNOWN
Classifier: Programming Language :: Python :: 3
Classifier: License :: OSI Approved :: MIT License
Classifier: Operating System :: OS Independent
Classifier: Topic :: Home Automation
Classifier: Topic :: System :: Monitoring
Classifier: Topic :: Software Development :: Libraries :: Python Modules
Classifier: Intended Audience :: Developers
Classifier: Intended Audience :: Information Technology
Requires-Python: >=3.4
